raman_hypmap/__init__.py
raman_hypmap/hyprocess.py
raman_hypmap-0.0.6.dist-info/METADATA
raman_hypmap-0.0.6.dist-info/WHEEL
raman_hypmap-0.0.6.dist-info/licenses/LICENSE
raman_hypmap-0.0.6.dist-info/RECORD
