Metadata-Version: 2.1
Name: raman_hypmap
Version: 0.0.6
Summary: Raman hyperspectral processing for Horiba instrument
Project-URL: Homepage, https://github.com/ag00dwin/raman_hypmap
Project-URL: Bug Tracker, https://https://github.com/ag00dwin/raman_hypmap/tree/main/.github/issues%20and%20feature%20request
Author: A Goodwin
License-File: LICENSE
Classifier: Intended Audience :: Science/Research
Classifier: License :: OSI Approved :: GNU General Public License v3 (GPLv3)
Classifier: Operating System :: Microsoft :: Windows
Classifier: Programming Language :: Python :: 3
Requires-Python: >=3.7
